setup.cfg
setup.py
tw.tools.egg-info/PKG-INFO
tw.tools.egg-info/SOURCES.txt
tw.tools.egg-info/dependency_links.txt
tw.tools.egg-info/entry_points.txt
tw.tools.egg-info/top_level.txt
tw.tools.egg-info/zip-safe
twtools/__init__.py
twtools/frameworks/__init__.py
twtools/frameworks/tg2/__init__.py
twtools/frameworks/tg2/activeform.py