Metadata-Version: 1.0
Name: tw.tools
Version: 0.8
Summary: Tools to aid toscawidget framework interactions.
Home-page: http://toscawidgets.org/
Author: Christopher Perkins
Author-email: chris@percious.com
License: MIT
Download-URL: http://toscawidgets.org/download
Keywords: toscawidgets widgets turbogears
Platform: UNKNOWN
